decryptor/__init__.py
decryptor/keypair.py
decryptor/message.py
decryptor/utils.py
discrete_rsa-0.1.dist-info/LICENSE
discrete_rsa-0.1.dist-info/METADATA
discrete_rsa-0.1.dist-info/WHEEL
discrete_rsa-0.1.dist-info/top_level.txt
discrete_rsa-0.1.dist-info/RECORD
