Metadata-Version: 2.1
Name: discrete-rsa
Version: 0.1
Summary: RSA decryptor stuff
Home-page: UNKNOWN
Author: Anonymous
Author-email: anonymous@idk.com
License: UNKNOWN
Platform: UNKNOWN
